{
  "id": "evt_3Qxss8E6hZ9WbPkk0KGt7sDa",
  "object": "event",
  "api_version": "2025-01-27.acacia",
  "created": 1740846403,
  "data": {
    "object": {
      "id": "ch_3Qxss8E6hZ9WbPkk072X5Fgd",
      "object": "charge",
      "amount": 4400,
      "amount_captured": 4400,
      "amount_refunded": 0,
      "application": null,
      "application_fee": null,
      "application_fee_amount": null,
      "balance_transaction": null,
      "billing_details": {
        "address": {
          "city": null,
          "country": "PR",
          "line1": null,
          "line2": null,
          "postal_code": null,
          "state": null
        },
        "email": "alexrimandones@hotmail.com",
        "name": "Alexander Roman",
        "phone": null
      },
      "calculated_statement_descriptor": "SKEDDLE GMBH",
      "captured": true,
      "created": 1740846402,
      "currency": "usd",
      "customer": "cus_Rrc55kfrTaqA9O",
      "description": null,
      "destination": null,
      "dispute": null,
      "disputed": false,
      "failure_balance_transaction": null,
      "failure_code": null,
      "failure_message": null,
      "fraud_details": {
      },
      "invoice": null,
      "livemode": true,
      "metadata": {
      },
      "on_behalf_of": null,
      "order": null,
      "outcome": {
        "advice_code": null,
        "network_advice_code": null,
        "network_decline_code": null,
        "network_status": "approved_by_network",
        "reason": null,
        "risk_level": "normal",
        "seller_message": "Payment complete.",
        "type": "authorized"
      },
      "paid": true,
      "payment_intent": "pi_3Qxss8E6hZ9WbPkk0keVYRnS",
      "payment_method": "pm_1Qxss7E6hZ9WbPkkZ4zhnAU1",
      "payment_method_details": {
        "card": {
          "amount_authorized": 4400,
          "authorization_code": "092982",
          "brand": "visa",
          "checks": {
            "address_line1_check": null,
            "address_postal_code_check": null,
            "cvc_check": "pass"
          },
          "country": "PR",
          "exp_month": 9,
          "exp_year": 2028,
          "extended_authorization": {
            "status": "disabled"
          },
          "fingerprint": "1EGBP6GqkMa73vm6",
          "funding": "debit",
          "incremental_authorization": {
            "status": "unavailable"
          },
          "installments": null,
          "last4": "8407",
          "mandate": null,
          "multicapture": {
            "status": "unavailable"
          },
          "network": "visa",
          "network_token": {
            "used": false
          },
          "network_transaction_id": "585060592020809",
          "overcapture": {
            "maximum_amount_capturable": 4400,
            "status": "unavailable"
          },
          "regulated_status": "regulated",
          "three_d_secure": {
            "authentication_flow": null,
            "electronic_commerce_indicator": "06",
            "exemption_indicator": null,
            "result": "attempt_acknowledged",
            "result_reason": null,
            "transaction_id": "6c0ffa90-91d9-46ca-864d-69d6b5f74d8e",
            "version": "2.2.0"
          },
          "wallet": null
        },
        "type": "card"
      },
      "radar_options": {
      },
      "receipt_email": null,
      "receipt_number": null,
      "receipt_url": "https://pay.stripe.com/receipts/payment/CAcQARoXChVhY2N0XzFRcTVGTUU2aFo5V2JQa2sow-qMvgYyBsuGOJZTPzosFkdnDD4G07M1sAY0h_qDffojc1GMowHGVOidBB7Qcui83cLO_WttrGvQ_Lg",
      "refunded": false,
      "review": null,
      "shipping": null,
      "source": null,
      "source_transfer": null,
      "statement_descriptor": null,
      "statement_descriptor_suffix": null,
      "status": "succeeded",
      "transfer_data": null,
      "transfer_group": null
    }
  },
  "livemode": true,
  "pending_webhooks": 1,
  "request": {
    "id": null,
    "idempotency_key": "pi_3Qxss8E6hZ9WbPkk0keVYRnS-payatt_3Qxss8E6hZ9WbPkk00l36Oj7"
  },
  "type": "charge.succeeded"
}